globalmart_api/__init__.py
globalmart_api/demo.py
globalmart_api_test-0.2.dist-info/License.txt
globalmart_api_test-0.2.dist-info/METADATA
globalmart_api_test-0.2.dist-info/WHEEL
globalmart_api_test-0.2.dist-info/top_level.txt
globalmart_api_test-0.2.dist-info/RECORD
