Metadata-Version: 2.1
Name: globalmart-api-test
Version: 0.2
Summary: Testing installation of Package
Author: Suchita Meshram
Author-email: suchitameshram28@gmail.com
License: MIT
License-File: License.txt
Requires-Dist: pandas
